pydbexport/__init__.py
pydbexport/export.py
pydbexport/main.py
pydbexport-1.0.dist-info/METADATA
pydbexport-1.0.dist-info/WHEEL
pydbexport-1.0.dist-info/top_level.txt
pydbexport-1.0.dist-info/RECORD
